st_pop_up_component/__init__.py
st_pop_up_component/frontend/build/asset-manifest.json
st_pop_up_component/frontend/build/bootstrap.min.css
st_pop_up_component/frontend/build/index.html
st_pop_up_component/frontend/build/static/js/2.a733c068.chunk.js
st_pop_up_component/frontend/build/static/js/2.a733c068.chunk.js.LICENSE.txt
st_pop_up_component/frontend/build/static/js/2.a733c068.chunk.js.map
st_pop_up_component/frontend/build/static/js/main.6500dfab.chunk.js
st_pop_up_component/frontend/build/static/js/main.6500dfab.chunk.js.map
st_pop_up_component/frontend/build/static/js/runtime-main.08bd5a01.js
st_pop_up_component/frontend/build/static/js/runtime-main.08bd5a01.js.map
st_pop_up_component-0.0.3.dist-info/LICENSE
st_pop_up_component-0.0.3.dist-info/METADATA
st_pop_up_component-0.0.3.dist-info/WHEEL
st_pop_up_component-0.0.3.dist-info/top_level.txt
st_pop_up_component-0.0.3.dist-info/RECORD
