Metadata-Version: 2.1
Name: st-pop-up-component
Version: 0.0.3
Summary: Using this component
Home-page: 
Author: Siva S
Author-email: 
Requires-Python: >=3.6
License-File: LICENSE
Requires-Dist: streamlit (>=0.63)
